abzer/__init__.py
abzer/__main__.py
abzer/abzer.py
abzer/const.py
abzer/util.py
abzer/version.py
abzer-0.3.1.dist-info/DESCRIPTION.rst
abzer-0.3.1.dist-info/METADATA
abzer-0.3.1.dist-info/RECORD
abzer-0.3.1.dist-info/WHEEL
abzer-0.3.1.dist-info/entry_points.txt
abzer-0.3.1.dist-info/metadata.json
abzer-0.3.1.dist-info/top_level.txt
