Metadata-Version: 2.0
Name: abzer
Version: 0.3.1
Summary: AcousticBrainz submission tool
Home-page: https://github.com/mineo/abzer
Author: Wieland Hoffmann
Author-email: themineo@gmail.com
License: MIT
Download-URL: https://github.com/mineo/abzer/tarball/master
Platform: UNKNOWN
Classifier: Development Status :: 4 - Beta
Classifier: License :: OSI Approved :: MIT License
Classifier: Natural Language :: English
Classifier: Operating System :: OS Independent
Classifier: Programming Language :: Python :: 3.5
Requires-Python: >=3.5
Requires-Dist: aiohttp
Provides-Extra: docs
Requires-Dist: sphinx; extra == 'docs'
Requires-Dist: sphinxcontrib-autoprogram; extra == 'docs'
